{".class": "MypyFile", "_fullname": "allennlp.training.initializer", "_name": null, "is_stub": false, "names": {".class": "SymbolTable", "Initializer": {".class": "SymbolTableNode", "kind": "Gdef", "node": {".class": "TypeInfo", "_promote": null, "abstract_attributes": [], "bases": ["allennlp.common.registrable.Registrable"], "declared_metaclass": null, "defn": {".class": "ClassDef", "fullname": "allennlp.training.initializer.Initializer", "metaclass": null, "name": "Initializer", "type_vars": []}, "flags": [], "fullname": "allennlp.training.initializer.Initializer", "metaclass_type": null, "module_name": "allennlp.training.initializer", "names": {".class": "SymbolTable", "default_implementation": {".class": "SymbolTableNode", "kind": "Mdef", "node": {".class": "Var", "flags": ["is_ready", "is_initialized_in_class"], "fullname": "allennlp.training.initializer.Initializer.default_implementation", "name": "default_implementation", "type": "builtins.str"}}}, "tuple_type": null, "type_vars": [], "typeddict_type": null}}, "Registrable": {".class": "SymbolTableNode", "cross_ref": "allennlp.common.registrable.Registrable", "kind": "Gdef"}, "__doc__": {".class": "SymbolTableNode", "kind": "Gdef", "node": {".class": "Var", "flags": ["is_ready"], "fullname": "allennlp.training.initializer.__doc__", "name": "__doc__", "type": "builtins.str"}}, "__file__": {".class": "SymbolTableNode", "kind": "Gdef", "node": {".class": "Var", "flags": ["is_ready"], "fullname": "allennlp.training.initializer.__file__", "name": "__file__", "type": "builtins.str"}}, "__name__": {".class": "SymbolTableNode", "kind": "Gdef", "node": {".class": "Var", "flags": ["is_ready"], "fullname": "allennlp.training.initializer.__name__", "name": "__name__", "type": "builtins.str"}}, "__package__": {".class": "SymbolTableNode", "kind": "Gdef", "node": {".class": "Var", "flags": ["is_ready"], "fullname": "allennlp.training.initializer.__package__", "name": "__package__", "type": "builtins.str"}}, "torch": {".class": "SymbolTableNode", "kind": "Gdef", "node": {".class": "Var", "flags": ["is_ready", "is_suppressed_import"], "fullname": "allennlp.training.initializer.torch", "name": "torch", "type": {".class": "AnyType"}}}}, "path": "/home/mattg/clone/allennlp/allennlp/training/initializer.py"}
