{"id": "data.dataset_readers.squad", "path": "/home/mattg/clone/allennlp/allennlp/data/dataset_readers/squad.py", "mtime": 1504544088, "size": 24206, "hash": "870f3660c6623fa88b3e7efc4922af02", "data_mtime": 1504544091, "dependencies": ["json", "logging", "random", "collections", "copy", "typing", "builtins"], "suppressed": ["numpy", "tqdm", "allennlp.common", "allennlp.common.checks", "allennlp.common.file_utils", "allennlp.data.dataset", "allennlp.data.dataset_readers.dataset_reader", "allennlp.data.instance", "allennlp.data.token_indexers.token_indexer", "allennlp.data.tokenizers.tokenizer", "allennlp.data.fields", "allennlp.data.tokenizers", "nltk"], "child_modules": [], "options": {"strict_optional": false, "ignore_missing_imports": true, "no_implicit_optional": false, "warn_no_return": true, "ignore_errors": false, "disallow_any": [], "disallow_untyped_defs": false, "follow_imports": "normal", "disallow_untyped_calls": false, "platform": "linux", "check_untyped_defs": false, "show_none_errors": true, "strict_optional_whitelist": null, "quick_and_dirty": false, "strict_boolean": false, "warn_return_any": false}, "dep_prios": [10, 10, 10, 5, 5, 5, 5], "interface_hash": "76d9f003aae639680dfafdacd5f3c684", "version_id": "0.521"}
