{"interface_hash": "2962d81c9b55fe02e0b4b65aeca60bf2", "hash": "de87b400ff2c23014a7fc65252633a7c", "version_id": "0.520", "child_modules": [], "path": "/home/mattg/clone/allennlp/allennlp/modules/similarity_functions/cosine.py", "mtime": 1501464453, "size": 1019, "id": "allennlp.modules.similarity_functions.cosine", "dependencies": ["allennlp.common", "allennlp.modules.similarity_function", "builtins"], "suppressed": [], "data_mtime": 1501464789, "dep_prios": [5, 5, 5], "options": {"strict_optional_whitelist": null, "quick_and_dirty": false, "strict_optional": false, "warn_no_return": true, "ignore_errors": false, "disallow_any": [], "strict_boolean": false, "warn_return_any": false, "debug_cache": false, "no_implicit_optional": false, "ignore_missing_imports": true, "follow_imports": "normal", "disallow_untyped_calls": false, "platform": "linux", "check_untyped_defs": false, "disallow_untyped_defs": false, "show_none_errors": true}}